{
  "courseList": [
    {
      "courseCode": "B_NURSING",
      "courseName": "BSc Nursing",
      "courseDetail": "",
      "collegeCode": "",
      "stateCode": "","sortoder":"",
      "duration":"4 Years"
    },
    {
      "courseCode": "B_MLT",
      "courseName": "BSc MLT",
      "courseDetail": "",
      "collegeCode": "",
      "stateCode": "","sortoder":"",
      "duration":"4 Years"
    },
    {
      "courseCode": "B_AEC",
      "courseName": "BSc Accident & Emergency Care",
      "courseDetail": "",
      "collegeCode": "",
      "stateCode": "","sortoder":"",
      "duration":"3 Years"
    },
    {
      "courseCode": "B_OA",
      "courseName": "BSc OT & AT",
      "courseDetail": "",
      "collegeCode": "",
      "stateCode": "","sortoder":"",
      "duration":"4 Years"
    },
    {
      "courseCode": "B_RI",
      "courseName": "BSc Radiography & Imaging Technology",
      "courseDetail": "",
      "collegeCode": "",
      "stateCode": "","sortoder":"",
      "duration":"4 Years"
    },
    {
      "courseCode": "B_CCT",
      "courseName": "BSc Cardiac Care Technology",
      "courseDetail": "",
      "collegeCode": "",
      "stateCode": "","sortoder":"",
      "duration":"4 Years"
    },
    {
      "courseCode": "B_DIALYSIS",
      "courseName": "BSc Dialysis",
      "courseDetail": "",
      "collegeCode": "",
      "stateCode": "","sortoder":"",
      "duration":"4 Years"
    },
    {
      "courseCode": "B_PA",
      "courseName": "BSc Physician Assistant",
      "courseDetail": "",
      "collegeCode": "",
      "stateCode": "","sortoder":"",
      "duration":"4 Years"
    },
    {
      "courseCode": "B_RT",
      "courseName": "BSc Radiotherapy",
      "courseDetail": "",
      "collegeCode": "",
      "stateCode": "","sortoder":"",
      "duration":"4 Years"
    },
    {
      "courseCode": "B_MIT",
      "courseName": "BSc Imaging Technology (MIT)",
      "courseDetail": "",
      "collegeCode": "",
      "stateCode": "","sortoder":"",
      "duration":"4 Years"
    },
    {
      "courseCode": "B_RESPERITORY",
      "courseName": "BSc Resperitory Therapy",
      "courseDetail": "",
      "collegeCode": "",
      "stateCode": "","sortoder":"",
      "duration":"4 Years"
    },
    {
      "courseCode": "M_NURSING",
      "courseName": "MSc Nursing",
      "courseDetail": "",
      "collegeCode": "",
      "stateCode": "","sortoder":"",
      "duration":"2 Years"
    },
    {
      "courseCode": "GNM",
      "courseName": "GNM Nursing",
      "courseDetail": "",
      "collegeCode": "",
      "stateCode": "","sortoder":"",
      "duration":"3 Years"
    },
    {
      "courseCode": "BPT",
      "courseName": "Physiotherapy (BPT)",
      "courseDetail": "",
      "collegeCode": "",
      "stateCode": "","sortoder":"",
      "duration":"4 Years"
    },
    {
      "courseCode": "D_PHARM",
      "courseName": "D PHARM",
      "courseDetail": "",
      "collegeCode": "",
      "stateCode": "","sortoder":"",
      "duration":"2 Years"
    },
    {
      "courseCode": "B_PHARM",
      "courseName": "B PHARM",
      "courseDetail": "",
      "collegeCode": "",
      "stateCode": "","sortoder":"",
      "duration":"4 Years"
    },
    {
      "courseCode": "M_PHARM",
      "courseName": "M PHARM",
      "courseDetail": "",
      "collegeCode": "",
      "stateCode": "","sortoder":"",
      "duration":"2 Years"
    },
    {
      "courseCode": "PHAM_D",
      "courseName": "PHAM D",
      "courseDetail": "",
      "collegeCode": "",
      "stateCode": "","sortoder":"",
      "duration":"6 Years"
    },
    {
      "courseCode": "AVIATION",
      "courseName": "Aviation Courses",
      "courseDetail": "",
      "collegeCode": "",
      "stateCode": "","sortoder":"",
      "duration":"3 Years"
    },
    {
      "courseCode": "HMC",
      "courseName": "Hotel Management Courses",
      "courseDetail": "",
      "collegeCode": "",
      "stateCode": "","sortoder":"",
      "duration":"3 Years"
    }
  ]
}